odoo8_addon_website_crm_recaptcha-8.0.1.0.0.99.dev8-py2.7-nspkg.pth
odoo8_addon_website_crm_recaptcha-8.0.1.0.0.99.dev8.dist-info/METADATA
odoo8_addon_website_crm_recaptcha-8.0.1.0.0.99.dev8.dist-info/RECORD
odoo8_addon_website_crm_recaptcha-8.0.1.0.0.99.dev8.dist-info/WHEEL
odoo8_addon_website_crm_recaptcha-8.0.1.0.0.99.dev8.dist-info/namespace_packages.txt
odoo8_addon_website_crm_recaptcha-8.0.1.0.0.99.dev8.dist-info/top_level.txt
odoo_addons/website_crm_recaptcha/README.rst
odoo_addons/website_crm_recaptcha/__init__.py
odoo_addons/website_crm_recaptcha/__openerp__.py
odoo_addons/website_crm_recaptcha/controllers/__init__.py
odoo_addons/website_crm_recaptcha/controllers/main.py
odoo_addons/website_crm_recaptcha/i18n/bg.po
odoo_addons/website_crm_recaptcha/i18n/es.po
odoo_addons/website_crm_recaptcha/i18n/eu.po
odoo_addons/website_crm_recaptcha/i18n/fr.po
odoo_addons/website_crm_recaptcha/i18n/it.po
odoo_addons/website_crm_recaptcha/i18n/pt_BR.po
odoo_addons/website_crm_recaptcha/i18n/sl.po
odoo_addons/website_crm_recaptcha/i18n/website_crm_recaptcha.pot
odoo_addons/website_crm_recaptcha/static/description/icon.png
odoo_addons/website_crm_recaptcha/views/website_crm_template.xml
