Metadata-Version: 2.1
Name: odoo8-addon-website-crm-recaptcha
Version: 8.0.1.0.0.99.dev8
Summary: Provides a ReCaptcha validation in Website Contact Form
Home-page: https://laslabs.com/
Author: LasLabs, Tecnativa, Odoo Community Association (OCA)
Author-email: support@odoo-community.org
License: AGPL-3
Platform: UNKNOWN
Classifier: Programming Language :: Python
Classifier: Framework :: Odoo
Classifier: License :: OSI Approved :: GNU Affero General Public License v3
Requires-Python: ~=2.7
Requires-Dist: odoo8-addon-website-form-recaptcha
Requires-Dist: odoo (<9.0a,>=8.0a)
